README.rst
setup.cfg
setup.py
lfmcli/__init__.py
lfmcli/api.py
lfmcli/cli.py
lfmcli/context.py
lfmcli/controller.py
lfmcli.egg-info/PKG-INFO
lfmcli.egg-info/SOURCES.txt
lfmcli.egg-info/dependency_links.txt
lfmcli.egg-info/entry_points.txt
lfmcli.egg-info/requires.txt
lfmcli.egg-info/top_level.txt
lfmcli.egg-info/zip-safe
lfmcli/commands/__init__.py
lfmcli/commands/cmd_controller.py
lfmcli/commands/cmd_eline.py
lfmcli/commands/cmd_etree.py
lfmcli/commands/cmd_ofnode.py
lfmcli/commands/cmd_path.py
lfmcli/commands/cmd_tap.py
lfmcli/commands/cmd_treepath.py