Metadata-Version: 1.1
Name: lfmcli
Version: 2.0.0
Summary: CLI and Python Binding Library for Lumina Flow Manager
Home-page: https://github.com/luminanetworks/lfm-cli
Author: Lumina Networks
Author-email: oss-dev@luminanetworks.com
License: LICENSE
Platform: UNKNOWN
Classifier: Development Status :: 2 - Pre-Alpha
Classifier: Programming Language :: Python
Classifier: Programming Language :: Python :: 2
Classifier: Programming Language :: Python :: 2.7
Classifier: Programming Language :: Python :: 3
Classifier: Programming Language :: Python :: 3.4
Classifier: Programming Language :: Python :: 3.5
